odoo8_addon_mail_optional_follower_notification-8.0.1.0.0.99.dev10-py2.7-nspkg.pth
odoo8_addon_mail_optional_follower_notification-8.0.1.0.0.99.dev10.dist-info/METADATA
odoo8_addon_mail_optional_follower_notification-8.0.1.0.0.99.dev10.dist-info/RECORD
odoo8_addon_mail_optional_follower_notification-8.0.1.0.0.99.dev10.dist-info/WHEEL
odoo8_addon_mail_optional_follower_notification-8.0.1.0.0.99.dev10.dist-info/namespace_packages.txt
odoo8_addon_mail_optional_follower_notification-8.0.1.0.0.99.dev10.dist-info/top_level.txt
odoo_addons/mail_optional_follower_notification/README.rst
odoo_addons/mail_optional_follower_notification/__init__.py
odoo_addons/mail_optional_follower_notification/__openerp__.py
odoo_addons/mail_optional_follower_notification/i18n/ca.po
odoo_addons/mail_optional_follower_notification/i18n/de.po
odoo_addons/mail_optional_follower_notification/i18n/el_GR.po
odoo_addons/mail_optional_follower_notification/i18n/es.po
odoo_addons/mail_optional_follower_notification/i18n/es_CO.po
odoo_addons/mail_optional_follower_notification/i18n/fi.po
odoo_addons/mail_optional_follower_notification/i18n/fr.po
odoo_addons/mail_optional_follower_notification/i18n/it.po
odoo_addons/mail_optional_follower_notification/i18n/mail_optional_follower_notification.pot
odoo_addons/mail_optional_follower_notification/i18n/nb.po
odoo_addons/mail_optional_follower_notification/i18n/pt_BR.po
odoo_addons/mail_optional_follower_notification/i18n/sl.po
odoo_addons/mail_optional_follower_notification/models/__init__.py
odoo_addons/mail_optional_follower_notification/models/mail_message.py
odoo_addons/mail_optional_follower_notification/models/mail_notification.py
odoo_addons/mail_optional_follower_notification/static/description/icon.png
odoo_addons/mail_optional_follower_notification/static/description/optional_follower_001.png
odoo_addons/mail_optional_follower_notification/static/description/optional_follower_002.png
odoo_addons/mail_optional_follower_notification/tests/__init__.py
odoo_addons/mail_optional_follower_notification/tests/test_mail_optional_follower_notifications.py
odoo_addons/mail_optional_follower_notification/wizard/__init__.py
odoo_addons/mail_optional_follower_notification/wizard/mail_compose_message.py
odoo_addons/mail_optional_follower_notification/wizard/mail_compose_message_view.xml
